README.rst
setup.py
darpy/__init__.py
darpy/common.py
darpy/constants.py
darpy/main.py
darpy/pack.py
darpy/unpack.py
darpy/version.py
darpy.egg-info/PKG-INFO
darpy.egg-info/SOURCES.txt
darpy.egg-info/dependency_links.txt
darpy.egg-info/entry_points.txt
darpy.egg-info/top_level.txt